eqparse/__init__.py
eqparse/loadsim.py
eqparse/plot.py
eqparse/hsr/__init__.py
eqparse/hsr/hsr.py
eqparse/hsr/plot.py
eqparse/hsr/unit_dict.py
eqparse/sim/__init__.py
eqparse/sim/batch.py
eqparse/sim/plot.py
eqparse/sim/sim.py
eqparse/spaceloads/__init__.py
eqparse/spaceloads/spaceloads.py
eqparse-0.0.2.dist-info/METADATA
eqparse-0.0.2.dist-info/WHEEL
eqparse-0.0.2.dist-info/top_level.txt
eqparse-0.0.2.dist-info/RECORD
