Metadata-Version: 2.1
Name: eqparse
Version: 0.0.2
Summary: reads SIM and HSR files produced by eQUEST simulations
Home-page: https://github.com/pypa/sampleproject
Author: Michael Sweeney
Author-email: michael.samuel.sweeney@gmail.com
License: UNKNOWN
Platform: UNKNOWN
Classifier: Programming Language :: Python :: 3
Classifier: License :: OSI Approved :: MIT License
Classifier: Operating System :: OS Independent
Requires-Python: >=3.6
